qwiic_i2c/__init__.py
qwiic_i2c/circuitpy_i2c.py
qwiic_i2c/i2c_driver.py
qwiic_i2c/linux_i2c.py
sparkfun_qwiic_i2c-0.9.11.dist-info/LICENSE
sparkfun_qwiic_i2c-0.9.11.dist-info/METADATA
sparkfun_qwiic_i2c-0.9.11.dist-info/WHEEL
sparkfun_qwiic_i2c-0.9.11.dist-info/top_level.txt
sparkfun_qwiic_i2c-0.9.11.dist-info/RECORD
